.gitignore
COPYING
MANIFEST.in
README.txt
requirements.txt
setup.py
bin/export_newsitems.py
ebpub/__init__.py
ebpub/constants.py
ebpub/geoadmin.py
ebpub/monkeypatches.py
ebpub/settings_default.py
ebpub/urls.py
ebpub.egg-info/PKG-INFO
ebpub.egg-info/SOURCES.txt
ebpub.egg-info/dependency_links.txt
ebpub.egg-info/entry_points.txt
ebpub.egg-info/requires.txt
ebpub.egg-info/top_level.txt
ebpub/accounts/__init__.py
ebpub/accounts/admin.py
ebpub/accounts/callbacks.py
ebpub/accounts/constants.py
ebpub/accounts/context_processors.py
ebpub/accounts/forms.py
ebpub/accounts/middleware.py
ebpub/accounts/models.py
ebpub/accounts/urls.py
ebpub/accounts/utils.py
ebpub/accounts/views.py
ebpub/accounts/management/__init__.py
ebpub/accounts/management/commands/__init__.py
ebpub/accounts/management/commands/createsuperuser.py
ebpub/accounts/migrations/0001_initial.py
ebpub/accounts/migrations/__init__.py
ebpub/alerts/__init__.py
ebpub/alerts/admin.py
ebpub/alerts/models.py
ebpub/alerts/sending.py
ebpub/alerts/views.py
ebpub/alerts/migrations/0001_initial.py
ebpub/alerts/migrations/0002_auto__add_field_emailalert_block_center.py
ebpub/alerts/migrations/0003_populate_block_center.py
ebpub/alerts/migrations/0004_auto__del_field_emailalert_block.py
ebpub/alerts/migrations/__init__.py
ebpub/db/__init__.py
ebpub/db/admin.py
ebpub/db/breadcrumbs.py
ebpub/db/constants.py
ebpub/db/context_processors.py
ebpub/db/feeds.py
ebpub/db/fields.py
ebpub/db/forms.py
ebpub/db/models.py
ebpub/db/schemafilters.py
ebpub/db/urlresolvers.py
ebpub/db/utils.py
ebpub/db/views.py
ebpub/db/bin/__init__.py
ebpub/db/bin/activate_schema.py
ebpub/db/bin/add_location.py
ebpub/db/bin/alphabetize_locations.py
ebpub/db/bin/delete_newsitems.py
ebpub/db/bin/export_schema.py
ebpub/db/bin/geocode_newsitems.py
ebpub/db/bin/import_hoods.py
ebpub/db/bin/import_locations.py
ebpub/db/bin/import_zips.py
ebpub/db/bin/update_aggregates.py
ebpub/db/fixtures/crimes.json
ebpub/db/fixtures/default_news_types.json
ebpub/db/fixtures/test-locationdetail-views.json
ebpub/db/fixtures/test-schemafilter-views.json
ebpub/db/management/__init__.py
ebpub/db/management/commands/__init__.py
